fabric/__init__.py
fabric/__main__.py
fabric/_version.py
fabric/config.py
fabric/connection.py
fabric/exceptions.py
fabric/executor.py
fabric/group.py
fabric/main.py
fabric/runners.py
fabric/tasks.py
fabric/transfer.py
fabric/tunnels.py
fabric/util.py
fabric/testing/__init__.py
fabric/testing/base.py
fabric/testing/fixtures.py
fabric_pr2042-2.5.0.dist-info/LICENSE
fabric_pr2042-2.5.0.dist-info/METADATA
fabric_pr2042-2.5.0.dist-info/WHEEL
fabric_pr2042-2.5.0.dist-info/entry_points.txt
fabric_pr2042-2.5.0.dist-info/top_level.txt
fabric_pr2042-2.5.0.dist-info/RECORD
