Metadata-Version: 2.1
Name: fabric-pr2042
Version: 2.5.0
Summary: High level SSH command execution
Home-page: http://fabfile.org
Author: Jeff Forcier
Author-email: jeff@bitprophet.org
License: BSD
Platform: UNKNOWN
Classifier: Development Status :: 5 - Production/Stable
Classifier: Environment :: Console
Classifier: Intended Audience :: Developers
Classifier: Intended Audience :: System Administrators
Classifier: License :: OSI Approved :: BSD License
Classifier: Operating System :: POSIX
Classifier: Operating System :: Unix
Classifier: Operating System :: MacOS :: MacOS X
Classifier: Operating System :: Microsoft :: Windows
Classifier: Programming Language :: Python
Classifier: Programming Language :: Python :: 2
Classifier: Programming Language :: Python :: 2.7
Classifier: Programming Language :: Python :: 3
Classifier: Programming Language :: Python :: 3.4
Classifier: Programming Language :: Python :: 3.5
Classifier: Programming Language :: Python :: 3.6
Classifier: Programming Language :: Python :: 3.7
Classifier: Topic :: Software Development
Classifier: Topic :: Software Development :: Build Tools
Classifier: Topic :: Software Development :: Libraries
Classifier: Topic :: Software Development :: Libraries :: Python Modules
Classifier: Topic :: System :: Clustering
Classifier: Topic :: System :: Software Distribution
Classifier: Topic :: System :: Systems Administration
Requires-Dist: invoke (<2.0,>=1.3)
Requires-Dist: paramiko (>=2.4)
Provides-Extra: pytest
Requires-Dist: mock (<3.0,>=2.0.0) ; extra == 'pytest'
Requires-Dist: pytest (<4.0,>=3.2.5) ; extra == 'pytest'
Provides-Extra: testing
Requires-Dist: mock (<3.0,>=2.0.0) ; extra == 'testing'
